stonutils/__init__.py
stonutils/account.py
stonutils/contract.py
stonutils/exceptions.py
stonutils/py.typed
stonutils/utils.py
stonutils/client/__init__.py
stonutils/client/_base.py
stonutils/client/lite.py
stonutils/client/tonapi.py
stonutils/client/toncenter.py
stonutils/dns/__init__.py
stonutils/dns/categories.py
stonutils/dns/contract.py
stonutils/dns/op_codes.py
stonutils/dns/utils.py
stonutils/dns/simple_subdomain/__init__.py
stonutils/dns/simple_subdomain/contract.py
stonutils/dns/simple_subdomain/data.py
stonutils/dns/simple_subdomain/op_codes.py
stonutils/jetton/__init__.py
stonutils/jetton/content.py
stonutils/jetton/data.py
stonutils/jetton/contract/__init__.py
stonutils/jetton/contract/stablecoin/__init__.py
stonutils/jetton/contract/stablecoin/master.py
stonutils/jetton/contract/stablecoin/op_codes.py
stonutils/jetton/contract/stablecoin/wallet.py
stonutils/jetton/contract/standard/__init__.py
stonutils/jetton/contract/standard/master.py
stonutils/jetton/contract/standard/op_codes.py
stonutils/jetton/contract/standard/wallet.py
stonutils/jetton/dex/__init__.py
stonutils/jetton/dex/dedust/__init__.py
stonutils/jetton/dex/dedust/exceptions.py
stonutils/jetton/dex/dedust/op_codes.py
stonutils/jetton/dex/dedust/contract/__init__.py
stonutils/jetton/dex/dedust/contract/asset.py
stonutils/jetton/dex/dedust/contract/factory.py
stonutils/jetton/dex/dedust/contract/pool.py
stonutils/jetton/dex/dedust/contract/vault.py
stonutils/nft/__init__.py
stonutils/nft/content.py
stonutils/nft/data.py
stonutils/nft/op_codes.py
stonutils/nft/royalty_params.py
stonutils/nft/contract/__init__.py
stonutils/nft/contract/base/__init__.py
stonutils/nft/contract/base/collection.py
stonutils/nft/contract/base/nft.py
stonutils/nft/contract/editable/__init__.py
stonutils/nft/contract/editable/collection.py
stonutils/nft/contract/editable/nft.py
stonutils/nft/contract/soulbound/__init__.py
stonutils/nft/contract/soulbound/collection.py
stonutils/nft/contract/soulbound/nft.py
stonutils-0.0.8.dist-info/LICENSE
stonutils-0.0.8.dist-info/METADATA
stonutils-0.0.8.dist-info/WHEEL
stonutils-0.0.8.dist-info/top_level.txt
stonutils-0.0.8.dist-info/RECORD
