Metadata-Version: 2.1
Name: stonutils
Version: 0.0.8
Summary: STonutils is a high-level, object-oriented Python library designed to facilitate seamless interactions with the TON blockchain.
Home-page: https://github.com/toantt208/ston-utils
Author: toantt208
License: MIT
Project-URL: Examples, https://github.com/toantt208/ston-utils/tree/main/examples
Project-URL: Source, https://github.com/toantt208/ston-utils
Project-URL: TON Blockchain, https://ton.org
Keywords: TON,The Open Network,TON blockchain,blockchain,crypto,asynchronous,smart contracts
Classifier: Development Status :: 4 - Beta
Classifier: Intended Audience :: Developers
Classifier: Intended Audience :: Financial and Insurance Industry
Classifier: Topic :: Software Development :: Libraries :: Python Modules
Classifier: Programming Language :: Python :: 3.10
Classifier: Programming Language :: Python :: 3.11
Classifier: Programming Language :: Python :: 3.12
Classifier: License :: OSI Approved :: MIT License
Classifier: Operating System :: OS Independent
Classifier: Framework :: AsyncIO
Classifier: Environment :: Console
Requires-Python: >=3.9
License-File: LICENSE
Requires-Dist: aiohttp~=3.9.5
Requires-Dist: pycryptodomex~=3.20.0
Requires-Dist: PyNaCl~=1.5.0
Requires-Dist: pytoniq-core~=0.1.36
Provides-Extra: pytoniq
Requires-Dist: pytoniq~=0.1.39; extra == "pytoniq"
